scaleway_async/__init__.py
scaleway_async/account/__init__.py
scaleway_async/account/v2/__init__.py
scaleway_async/account/v2/api.py
scaleway_async/account/v2/marshalling.py
scaleway_async/account/v2/types.py
scaleway_async/account/v3/__init__.py
scaleway_async/account/v3/api.py
scaleway_async/account/v3/marshalling.py
scaleway_async/account/v3/types.py
scaleway_async/applesilicon/__init__.py
scaleway_async/applesilicon/v1alpha1/__init__.py
scaleway_async/applesilicon/v1alpha1/api.py
scaleway_async/applesilicon/v1alpha1/content.py
scaleway_async/applesilicon/v1alpha1/marshalling.py
scaleway_async/applesilicon/v1alpha1/types.py
scaleway_async/audit_trail/__init__.py
scaleway_async/audit_trail/v1alpha1/__init__.py
scaleway_async/audit_trail/v1alpha1/api.py
scaleway_async/audit_trail/v1alpha1/marshalling.py
scaleway_async/audit_trail/v1alpha1/types.py
scaleway_async/autoscaling/__init__.py
scaleway_async/autoscaling/v1alpha1/__init__.py
scaleway_async/autoscaling/v1alpha1/api.py
scaleway_async/autoscaling/v1alpha1/marshalling.py
scaleway_async/autoscaling/v1alpha1/types.py
scaleway_async/baremetal/__init__.py
scaleway_async/baremetal/v1/__init__.py
scaleway_async/baremetal/v1/api.py
scaleway_async/baremetal/v1/content.py
scaleway_async/baremetal/v1/marshalling.py
scaleway_async/baremetal/v1/types.py
scaleway_async/baremetal/v3/__init__.py
scaleway_async/baremetal/v3/api.py
scaleway_async/baremetal/v3/content.py
scaleway_async/baremetal/v3/marshalling.py
scaleway_async/baremetal/v3/types.py
scaleway_async/billing/__init__.py
scaleway_async/billing/v2alpha1/__init__.py
scaleway_async/billing/v2alpha1/api.py
scaleway_async/billing/v2alpha1/marshalling.py
scaleway_async/billing/v2alpha1/types.py
scaleway_async/billing/v2beta1/__init__.py
scaleway_async/billing/v2beta1/api.py
scaleway_async/billing/v2beta1/marshalling.py
scaleway_async/billing/v2beta1/types.py
scaleway_async/block/__init__.py
scaleway_async/block/v1/__init__.py
scaleway_async/block/v1/api.py
scaleway_async-2.10.3.dist-info/METADATA
scaleway_async-2.10.3.dist-info/WHEEL
scaleway_async-2.10.3.dist-info/RECORD
